QQHong/__init__.py
QQHong/tools.py
QQHong/resource/__init__.py
QQHong/resource/cert.crt
QQHong/resource/private.key
QQHong/resource/headers/User-Agent
QQHong-0.0.70.dist-info/METADATA
QQHong-0.0.70.dist-info/WHEEL
QQHong-0.0.70.dist-info/top_level.txt
QQHong-0.0.70.dist-info/RECORD
