Metadata-Version: 2.1
Name: QQHong
Version: 0.0.70
Summary: QQHong's library
Home-page: UNKNOWN
Author: QQHong
License: UNKNOWN
Platform: UNKNOWN
Requires-Python: >=3
Requires-Dist: pymongo
Requires-Dist: selenium
Requires-Dist: pillow
Requires-Dist: pycryptodome
Requires-Dist: exrex
